cli_override/__init__.py
cli_override/parser.py
cli_override-0.0.1.dist-info/LICENSE.txt
cli_override-0.0.1.dist-info/METADATA
cli_override-0.0.1.dist-info/WHEEL
cli_override-0.0.1.dist-info/top_level.txt
cli_override-0.0.1.dist-info/RECORD
