Metadata-Version: 2.1
Name: cli-override
Version: 0.0.1
Summary: Cli Override
Home-page: https://github.com/blester125/cli-override
Download-URL: https://github.com/blester125/cli-override/archive/0.0.1.tar.gz
Author: blester125
Author-email: blester125@gmail.com
License: MIT
Classifier: Intended Audience :: Science/Research
Classifier: Environment :: Console
Classifier: License :: OSI Approved :: MIT License
Classifier: Topic :: Scientific/Engineering
Classifier: Intended Audience :: Developers
Classifier: Programming Language :: Python :: 3 :: Only
Classifier: Development Status :: 3 - Alpha
Classifier: Natural Language :: English
Requires-Python: >=3.6
License-File: LICENSE.txt
Provides-Extra: test
Requires-Dist: pytest; extra == "test"
